asyncshadow/__init__.py
asyncshadow/acm.py
asyncshadow/client.py
asyncshadow/socket.py
asyncshadow/sub_client.py
lib/__init__.py
shadowamino-1.0.0.dist-info/METADATA
shadowamino-1.0.0.dist-info/WHEEL
shadowamino-1.0.0.dist-info/top_level.txt
shadowamino-1.0.0.dist-info/RECORD
