Metadata-Version: 2.1
Name: shadowamino
Version: 1.0.0
Summary: Aminoapps lib for Python
Home-page: https://instagram.com/po60
Author: Shadow
Author-email: tmhat2374@gmail.com
Classifier: Programming Language :: Python :: 3
Classifier: License :: OSI Approved :: MIT License
Classifier: Operating System :: OS Independent
Requires-Python: >=3.6
